{
    "currentFloor": 1,
    "mapData": [
        {
            "floor": 0,
            "isBossKill": false,
            "onCristalList": [],
            "openChestList": [],
            "killUniqueEnemy": []
        },
        {
            "floor": 1,
            "isBossKill": false,
            "onCristalList": [
                1,
                0,
                19,
                15,
                2,
                21,
                25,
                26,
                22
            ],
            "openChestList": [],
            "killUniqueEnemy": []
        },
        {
            "floor": 2,
            "isBossKill": false,
            "onCristalList": [],
            "openChestList": [],
            "killUniqueEnemy": []
        },
        {
            "floor": 3,
            "isBossKill": false,
            "onCristalList": [],
            "openChestList": [],
            "killUniqueEnemy": []
        }
    ]
}